[
  {
    "rj_code": "RJ01405104",
    "site_id": "maniax",
    "title": "【本編関連の音声CG動画105点】目と耳で一緒に過ごす夏休み♪LINEハメ撮りチェキ日記で更に妄想楽しく♪～夏、まっサカり～ 女友達が俺を取り合い?！贅沢ハーレム【4時間】",
    "circle": "猫麦",
    "release_date": "2025年08月09日",
    "description": "◆本編に関わる【おまけイラスト&ハメ撮りたち】で更に本編が楽しめる♪◆\n\n    \n    \n          \n\n        \n\n          \n\n                                \n\n                        \n\n          \n\n            \n✨◆本編に関わる【夏休みの思い出チェキ集&ハメ撮り】で、この夏、2人と一緒に過ごした気分になれるっ♪✨\n\r\n\n\r\n現在の特典一覧\n\r\n\n\r\n◆夏休みイラスト各種原画配布◆\n\r\n\n\r\n【基本絵柄…全27種(計103枚)】\n\r\nーーーハメ撮りHCG&LINE画3種(セリフ射精等差分20枚)\n\r\nーーー夏休みの思い出チェキ13種(+衣装差分1枚)\n\r\nーーーおまけエピソード漫画2種\n\r\nーーーえっちな水着お披露目2種(衣装差分10枚)\n\r\nーーージャケ絵(差分イロイロ10枚)\n\r\nーーー他おまけイラスト6種\n\r\nーーー文字無し差分41枚\n\r\n\n\r\n◆他、オナサポなど音声特典もついてくるっ！✨\n\r\nーーー購入特典オナサポ2種\n\r\nーーー追加記念動画2種(セリフ無し+2)計4本✨\n\r\n\n\r\n※翻訳版は、追加分イラストは後日追加されますので、お得なうちに購入して楽しみに待っててくださいねっ♪\n\n          \n\n        \n\n      \n\n\n\n    \n\n\n            \n  \n\n\n\n              \n◆キャラ紹介◆\n\n    \n    \n          \n\n        \n\n          \n\n                                \n\n                        \n\n          \n\n            \n■【ちっぱい強がりM・愛野メシア】CV柚木つばめ 様\n\r\n「うぐ…これから大きくなるんだもんっ」\n\r\n\n\r\n・全体的に抱っこしやすそうな体型\n\r\n・めいみたいにイロイロ大きくなりたい、実は胸はコンプレックス\n\r\n・普段しっかり者だけど、めいと君には甘えてわがまま言っちゃう\n\r\n・夏休みの宿題はいつもギリギリでめいに泣きつくタイプ\n\r\n・自分に自信が無いせいか、性的に求められると応えたくなっちゃう\n\r\n\n\r\n\n\r\n\n\r\n■【巨乳あまあまS・佐藤めい】CV:陽向葵ゅか 様\n\r\n「こんなのただの…遺伝だから…っ」\n\r\n\n\r\n・高身長、最近栄養が全部胸に行くのが悩み\n\r\n・優等生、人見知りだけど君とメシアは大好き\n\r\n・一緒の大学に行きたいのでメシアに少しでも勉強頑張って欲しいと思ってる\n\r\n・夏休みの宿題は先に終わらせ、予習もするタイプ\n\r\n・君とメシアの反応が可愛くて、ついついイジワルしたくなっちゃう\n\r\n\n\r\n◆今度の世界線のキミはめいちゃんと同級生?！\n\r\nこの関係、どうなる?！\n\n          \n\n        \n\n      \n\n\n\n    \n\n\n            \n  \n\n\n\n              \n◆【CONCEPT】【STORY】◆\n\n    \n    \n          \n\n        \n\n          \n\n                                \n\n                        \n\n          \n\n            \n【CONCEPT】\n\r\n今回も作者の癖をいっぱい詰めましたっ\n\r\n\n\r\n・体格も性格も性癖まで…♪\n\r\n…全部が真逆のヒロイン2人との汗だくSEX！\n\r\n\n\r\n【初めてのハーレム作品♪】\n\r\nせっかくなので、各ヒロインとの【抜けがけ、内緒の隠姦シチュ】以外は、ぜーーんぶのトラックをハーレムにしてみましたっ！\n\r\n\n\r\n・強がりMのメシアちゃん、あまあまSのめいちゃん、\n\r\n…タイプが真逆の2人に同時に求められちゃうっ\n\r\n\n\r\n・いろんな場所で、いろんなシチュで…！ \n\r\n…夏の思い出作っちゃおう♪\n\r\n\n\r\n・大小不揃いなWパイズリ♪がんばれメシア！\n\r\n・片方にバレないように声我慢！背徳感SEX！\n\r\n・徐々に増してく君への好意、どっちから気付いてる??\n\r\n\n\r\n\n\r\n【STORY】\n\r\n『～ひと夏で何度も美味しい凸凹コンビ♪～』\n\r\n【貧乳】　×　【爆乳】　ハーレム！！！…♪\n\r\n\n\r\n\n\r\n・夏休みの宿題が全然終わらないメシアの為に、僕の部屋で勉強会！\n\r\n…のはずが、本人はのんきに宝探し。エロ本みーっけ！\n\r\n\n\r\n・集中してる僕らにバレないように読んでたらムラムラしちゃって、1人布団の中でもぞもぞ…\n\r\n\n\r\n『メシアちゃーん?なーにしてるのかな???』\n\r\n\n\r\n焦るメシアと勃起する僕と………わるーーーい顔のめいちゃん…♪\n\r\n\n\r\n『他、海でも！帰りのバスでも！通話中も…』\n\r\n\n\r\n【仲良く3人で??こっそり2人で??\n\r\n今年の夏は一緒に思い出つくろうね♪♪】\n\n          \n\n        \n\n      \n\n\n\n    \n\n\n            \n  \n\n\n\n              \n✨◆特典一覧◆✨\n\n    \n    \n          \n\n        \n\n          \n\n                                \n\n                        \n\n          \n\n            \n✨◆【購入特典▶イラスト103枚、オナサポ2本、テキスト台本】\n\r\n◆特典01　2人で上手にお手伝いできるかな?♪オナサポ1♪\n\r\n◆特典02　3人で一緒にオナニーしよ♪オナサポ2♪\n\r\n◆特典03　ジャケ絵原画&差分etc…♪\n\r\n◆特典04　君とえっち中のめいちゃん♪&差分etc…♪\n\r\n◆特典05　君とエッチ中のメシアちゃん♪&差分etc…♪\n\r\n◆特典06　君と過ごした夏休みの思い出♪詰め合わせ♪\n\n          \n\n        \n\n      \n\n\n\n    \n\n\n            \n  \n\n\n\n              \n◆【TRACKLIST】◆\n\n    \n    \n          \n\n        \n・総再生時間　(264分09秒)　(4時間24分09秒)\n\r\n・効果音無し差分込み　(528分18秒)　(8時間48分18秒)\n\r\n\n\r\n\n\r\n1章   「プロローグ」　夏休みのある日……同じクラスのJK2人と僕の部屋で宿題中…♪　(03:05)\n\r\n\n\r\n2章　「エロマンガ発見～♪」　興奮したメシアの布団に隠れてこっそり密室声我慢オナニー…♪　(11:25)\n\r\n\n\r\n3章　「オナばれ♪ 勃起チンポ、見たかったのかもね…♪」　めいとメシアの発情オナ見せ手コキ…♪　(23:08)\n\r\n\n\r\n4章　「おまんこ気持ちよくされるのだめ♪」　メシアにご褒美手マン……♪　めいにもフェラとイラマで精液プレゼント♪　(13:30)\n\r\n\n\r\n5章　「勃起おチンポ、ここに入れていいよ?」　Wパイズリフェラで勃起復活♪　からのダブルJK連続えっち♪　(27:09)\n\r\n\n\r\n6章　「おまんこ屈服させられてイグ……♪」　絶倫チンポで無双セックス♪　ダブルオホ声強烈アクメ…♪　(28:47)\n\r\n\n\r\n7章　「せっかくの夏休みなんだし……♪」　セックス終わりのゆったりお休みタイム……♪　次の約束は……♪　(09:17)\n\r\n\n\r\n8章　「ちんちんなんか好きじゃないもん……♪」　海に到着　シャワールームでこっそりえっち…♪　(27:33)\n\r\n\n\r\n9章　「何にも気にしないで、おチンポハメて♪」　シャワールームで連続いちゃいちゃセックス……♪　(27:37)\n\r\n\n\r\n10章　「めいには内緒で……♪」　帰りの夜行バスでメシアとひそひそえっち……♪　気持ち良すぎて何度もイックっ…♪　(33:08)\n\r\n\n\r\n11章　「メシアに聞かれちゃうから……♪」　めいの家で興奮即えっち♪　通話中に聞こえないように……♪　(29:31)\n\r\n\n\r\n12章　「エピローグ」　待ち合わせ先で、めいとメシアのガールズトークが聞こえてきて……♪　(03:44)\n\r\n\n\r\n・スタジオ収録　(48khz・24bit)\n\r\n・全編バイノーラルマイク【KU100】仕様\n\n      \n\n\n    \n\n\n            \n  \n\n\n\n              \n◆【CREDIT】◆\n\n    \n    \n          \n\n        \n◆最後まで読んでくれてありがとうございましたっ！\n\r\nこれを手に取った皆さんが、えっちでハッピーな気分で寝れますようにっ✨\n\r\n\n\r\n他の作品が気になるよ～て方は、普段各支援サイトでオリキャラたちの漫画を描いています。\n\r\nたまに無料公開もしていますので、気軽に遊びに来てください～\n\r\nファンボックス)\nhttps://nekom.fanbox.cc/\n\r\nファンティア)\nhttps://fantia.jp/fanclubs/23611\n\r\n\n\r\n\n\r\n・企画・プロット・イラスト:猫麦(@09ra_19ra)\n\r\n・音声制作:マヨタマ様(@_mayotama_)\n\r\n・CV:柚木つばめ様(@re_re_tsubame)\n\r\n・CV:陽向葵ゅか様(@yukanyan2525)\n\r\n・ロゴ・デザイン:nzworks様(@_nzworks_)\n\r\n・シナリオ:白鴉鼎様(@hakuakanae)\n\r\n・音声編集:atelier AUTH_QUID様\n\r\n・映像制作: GriOni:柴田 裕也様",
    "img_url": "//img.dlsite.jp/modpub/images2/work/doujin/RJ01406000/RJ01405104_img_main.jpg",
    "media": [
      "https://img.dlsite.jp/modpub/images2/work/doujin/RJ01406000/RJ01405104_img_main.jpg",
      "https://img.dlsite.jp/modpub/images2/work/doujin/RJ01406000/RJ01405104_img_smp1.jpg",
      "https://img.dlsite.jp/modpub/images2/work/doujin/RJ01406000/RJ01405104_img_smp2.jpg",
      "https://img.dlsite.jp/modpub/images2/work/doujin/RJ01406000/RJ01405104_img_smp3.jpg",
      "https://img.dlsite.jp/modpub/images2/work/doujin/RJ01406000/RJ01405104_img_smp4.jpg",
      "https://img.dlsite.jp/modpub/images2/work/doujin/RJ01406000/RJ01405104_img_smp5.jpg",
      "https://img.dlsite.jp/modpub/images2/work/doujin/RJ01406000/RJ01405104_img_smp6.jpg",
      "https://img.dlsite.jp/modpub/images2/work/doujin/RJ01406000/RJ01405104_img_smp7.jpg",
      "https://img.dlsite.jp/modpub/images2/work/doujin/RJ01406000/RJ01405104_img_smp8.jpg",
      "https://img.dlsite.jp/modpub/images2/work/doujin/RJ01406000/RJ01405104_img_smp9.jpg",
      "https://img.dlsite.jp/modpub/images2/work/doujin/RJ01406000/RJ01405104_img_smp10.jpg"
    ],
    "embeds": [],
    "chobit_url": "https://chobit.cc/embed/3jlam/50crmq4j?aid=gentleman_dl",
    "genres": [
      "2cv",
      "ASMR",
      "バイノーラル/ダミヘ",
      "同級生/同僚",
      "ハーレム",
      "ささやき",
      "中出し",
      "巨乳/爆乳",
      "貧乳/微乳"
    ],
    "cv": [
      "柚木つばめ",
      "陽向葵ゅか"
    ],
    "content_tokens": [
      {
        "type": "text",
        "content": "◆本編に関わる【おまけイラスト&ハメ撮りたち】で更に本編が楽しめる♪◆"
      },
      {
        "type": "image",
        "url": "https://img.dlsite.jp/modpub/images2/parts/RJ01406000/RJ01405104/2d64058b3411d40b37dd5010ec0b3b07.jpg"
      },
      {
        "type": "text",
        "content": "✨◆本編に関わる【夏休みの思い出チェキ集&ハメ撮り】で、この夏、2人と一緒に過ごした気分になれるっ♪✨"
      },
      {
        "type": "text",
        "content": "\r\n現在の特典一覧"
      },
      {
        "type": "text",
        "content": "\r\n◆夏休みイラスト各種原画配布◆"
      },
      {
        "type": "text",
        "content": "\r\n【基本絵柄…全27種(計103枚)】"
      },
      {
        "type": "text",
        "content": "\r\nーーーハメ撮りHCG&LINE画3種(セリフ射精等差分20枚)"
      },
      {
        "type": "text",
        "content": "\r\nーーー夏休みの思い出チェキ13種(+衣装差分1枚)"
      },
      {
        "type": "text",
        "content": "\r\nーーーおまけエピソード漫画2種"
      },
      {
        "type": "text",
        "content": "\r\nーーーえっちな水着お披露目2種(衣装差分10枚)"
      },
      {
        "type": "text",
        "content": "\r\nーーージャケ絵(差分イロイロ10枚)"
      },
      {
        "type": "text",
        "content": "\r\nーーー他おまけイラスト6種"
      },
      {
        "type": "text",
        "content": "\r\nーーー文字無し差分41枚"
      },
      {
        "type": "text",
        "content": "\r\n◆他、オナサポなど音声特典もついてくるっ！✨"
      },
      {
        "type": "text",
        "content": "\r\nーーー購入特典オナサポ2種"
      },
      {
        "type": "text",
        "content": "\r\nーーー追加記念動画2種(セリフ無し+2)計4本✨"
      },
      {
        "type": "text",
        "content": "\r\n※翻訳版は、追加分イラストは後日追加されますので、お得なうちに購入して楽しみに待っててくださいねっ♪"
      },
      {
        "type": "text",
        "content": "◆キャラ紹介◆"
      },
      {
        "type": "image",
        "url": "https://img.dlsite.jp/modpub/images2/parts/RJ01406000/RJ01405104/59db23a6f2ceab523912f0345c66364d.jpg"
      },
      {
        "type": "text",
        "content": "■【ちっぱい強がりM・愛野メシア】CV柚木つばめ 様"
      },
      {
        "type": "text",
        "content": "\r\n「うぐ…これから大きくなるんだもんっ」"
      },
      {
        "type": "text",
        "content": "\r\n・全体的に抱っこしやすそうな体型"
      },
      {
        "type": "text",
        "content": "\r\n・めいみたいにイロイロ大きくなりたい、実は胸はコンプレックス"
      },
      {
        "type": "text",
        "content": "\r\n・普段しっかり者だけど、めいと君には甘えてわがまま言っちゃう"
      },
      {
        "type": "text",
        "content": "\r\n・夏休みの宿題はいつもギリギリでめいに泣きつくタイプ"
      },
      {
        "type": "text",
        "content": "\r\n・自分に自信が無いせいか、性的に求められると応えたくなっちゃう"
      },
      {
        "type": "text",
        "content": "\r\n■【巨乳あまあまS・佐藤めい】CV:陽向葵ゅか 様"
      },
      {
        "type": "text",
        "content": "\r\n「こんなのただの…遺伝だから…っ」"
      },
      {
        "type": "text",
        "content": "\r\n・高身長、最近栄養が全部胸に行くのが悩み"
      },
      {
        "type": "text",
        "content": "\r\n・優等生、人見知りだけど君とメシアは大好き"
      },
      {
        "type": "text",
        "content": "\r\n・一緒の大学に行きたいのでメシアに少しでも勉強頑張って欲しいと思ってる"
      },
      {
        "type": "text",
        "content": "\r\n・夏休みの宿題は先に終わらせ、予習もするタイプ"
      },
      {
        "type": "text",
        "content": "\r\n・君とメシアの反応が可愛くて、ついついイジワルしたくなっちゃう"
      },
      {
        "type": "text",
        "content": "\r\n◆今度の世界線のキミはめいちゃんと同級生?！"
      },
      {
        "type": "text",
        "content": "\r\nこの関係、どうなる?！"
      },
      {
        "type": "text",
        "content": "◆【CONCEPT】【STORY】◆"
      },
      {
        "type": "image",
        "url": "https://img.dlsite.jp/modpub/images2/parts/RJ01406000/RJ01405104/e756745d5a19282e7ff9eb20e3e4be4c.jpg"
      },
      {
        "type": "text",
        "content": "【CONCEPT】"
      },
      {
        "type": "text",
        "content": "\r\n今回も作者の癖をいっぱい詰めましたっ"
      },
      {
        "type": "text",
        "content": "\r\n・体格も性格も性癖まで…♪"
      },
      {
        "type": "text",
        "content": "\r\n…全部が真逆のヒロイン2人との汗だくSEX！"
      },
      {
        "type": "text",
        "content": "\r\n【初めてのハーレム作品♪】"
      },
      {
        "type": "text",
        "content": "\r\nせっかくなので、各ヒロインとの【抜けがけ、内緒の隠姦シチュ】以外は、ぜーーんぶのトラックをハーレムにしてみましたっ！"
      },
      {
        "type": "text",
        "content": "\r\n・強がりMのメシアちゃん、あまあまSのめいちゃん、"
      },
      {
        "type": "text",
        "content": "\r\n…タイプが真逆の2人に同時に求められちゃうっ"
      },
      {
        "type": "text",
        "content": "\r\n・いろんな場所で、いろんなシチュで…！ "
      },
      {
        "type": "text",
        "content": "\r\n…夏の思い出作っちゃおう♪"
      },
      {
        "type": "text",
        "content": "\r\n・大小不揃いなWパイズリ♪がんばれメシア！"
      },
      {
        "type": "text",
        "content": "\r\n・片方にバレないように声我慢！背徳感SEX！"
      },
      {
        "type": "text",
        "content": "\r\n・徐々に増してく君への好意、どっちから気付いてる??"
      },
      {
        "type": "text",
        "content": "\r\n【STORY】"
      },
      {
        "type": "text",
        "content": "\r\n『～ひと夏で何度も美味しい凸凹コンビ♪～』"
      },
      {
        "type": "text",
        "content": "\r\n【貧乳】　×　【爆乳】　ハーレム！！！…♪"
      },
      {
        "type": "text",
        "content": "\r\n・夏休みの宿題が全然終わらないメシアの為に、僕の部屋で勉強会！"
      },
      {
        "type": "text",
        "content": "\r\n…のはずが、本人はのんきに宝探し。エロ本みーっけ！"
      },
      {
        "type": "text",
        "content": "\r\n・集中してる僕らにバレないように読んでたらムラムラしちゃって、1人布団の中でもぞもぞ…"
      },
      {
        "type": "text",
        "content": "\r\n『メシアちゃーん?なーにしてるのかな???』"
      },
      {
        "type": "text",
        "content": "\r\n焦るメシアと勃起する僕と………わるーーーい顔のめいちゃん…♪"
      },
      {
        "type": "text",
        "content": "\r\n『他、海でも！帰りのバスでも！通話中も…』"
      },
      {
        "type": "text",
        "content": "\r\n【仲良く3人で??こっそり2人で??"
      },
      {
        "type": "text",
        "content": "\r\n今年の夏は一緒に思い出つくろうね♪♪】"
      },
      {
        "type": "text",
        "content": "✨◆特典一覧◆✨"
      },
      {
        "type": "image",
        "url": "https://img.dlsite.jp/modpub/images2/parts/RJ01406000/RJ01405104/9599951ef3e75d0477d0de99bd8be485.jpg"
      },
      {
        "type": "text",
        "content": "✨◆【購入特典▶イラスト103枚、オナサポ2本、テキスト台本】"
      },
      {
        "type": "text",
        "content": "\r\n◆特典01　2人で上手にお手伝いできるかな?♪オナサポ1♪"
      },
      {
        "type": "text",
        "content": "\r\n◆特典02　3人で一緒にオナニーしよ♪オナサポ2♪"
      },
      {
        "type": "text",
        "content": "\r\n◆特典03　ジャケ絵原画&差分etc…♪"
      },
      {
        "type": "text",
        "content": "\r\n◆特典04　君とえっち中のめいちゃん♪&差分etc…♪"
      },
      {
        "type": "text",
        "content": "\r\n◆特典05　君とエッチ中のメシアちゃん♪&差分etc…♪"
      },
      {
        "type": "text",
        "content": "\r\n◆特典06　君と過ごした夏休みの思い出♪詰め合わせ♪"
      },
      {
        "type": "text",
        "content": "◆【TRACKLIST】◆"
      },
      {
        "type": "text",
        "content": "・総再生時間　(264分09秒)　(4時間24分09秒)"
      },
      {
        "type": "text",
        "content": "\r\n・効果音無し差分込み　(528分18秒)　(8時間48分18秒)"
      },
      {
        "type": "text",
        "content": "\r\n1章   「プロローグ」　夏休みのある日……同じクラスのJK2人と僕の部屋で宿題中…♪　(03:05)"
      },
      {
        "type": "text",
        "content": "\r\n2章　「エロマンガ発見～♪」　興奮したメシアの布団に隠れてこっそり密室声我慢オナニー…♪　(11:25)"
      },
      {
        "type": "text",
        "content": "\r\n3章　「オナばれ♪ 勃起チンポ、見たかったのかもね…♪」　めいとメシアの発情オナ見せ手コキ…♪　(23:08)"
      },
      {
        "type": "text",
        "content": "\r\n4章　「おまんこ気持ちよくされるのだめ♪」　メシアにご褒美手マン……♪　めいにもフェラとイラマで精液プレゼント♪　(13:30)"
      },
      {
        "type": "text",
        "content": "\r\n5章　「勃起おチンポ、ここに入れていいよ?」　Wパイズリフェラで勃起復活♪　からのダブルJK連続えっち♪　(27:09)"
      },
      {
        "type": "text",
        "content": "\r\n6章　「おまんこ屈服させられてイグ……♪」　絶倫チンポで無双セックス♪　ダブルオホ声強烈アクメ…♪　(28:47)"
      },
      {
        "type": "text",
        "content": "\r\n7章　「せっかくの夏休みなんだし……♪」　セックス終わりのゆったりお休みタイム……♪　次の約束は……♪　(09:17)"
      },
      {
        "type": "text",
        "content": "\r\n8章　「ちんちんなんか好きじゃないもん……♪」　海に到着　シャワールームでこっそりえっち…♪　(27:33)"
      },
      {
        "type": "text",
        "content": "\r\n9章　「何にも気にしないで、おチンポハメて♪」　シャワールームで連続いちゃいちゃセックス……♪　(27:37)"
      },
      {
        "type": "text",
        "content": "\r\n10章　「めいには内緒で……♪」　帰りの夜行バスでメシアとひそひそえっち……♪　気持ち良すぎて何度もイックっ…♪　(33:08)"
      },
      {
        "type": "text",
        "content": "\r\n11章　「メシアに聞かれちゃうから……♪」　めいの家で興奮即えっち♪　通話中に聞こえないように……♪　(29:31)"
      },
      {
        "type": "text",
        "content": "\r\n12章　「エピローグ」　待ち合わせ先で、めいとメシアのガールズトークが聞こえてきて……♪　(03:44)"
      },
      {
        "type": "text",
        "content": "\r\n・スタジオ収録　(48khz・24bit)"
      },
      {
        "type": "text",
        "content": "\r\n・全編バイノーラルマイク【KU100】仕様"
      },
      {
        "type": "text",
        "content": "◆【CREDIT】◆"
      },
      {
        "type": "text",
        "content": "◆最後まで読んでくれてありがとうございましたっ！"
      },
      {
        "type": "text",
        "content": "\r\nこれを手に取った皆さんが、えっちでハッピーな気分で寝れますようにっ✨"
      },
      {
        "type": "text",
        "content": "\r\n他の作品が気になるよ～て方は、普段各支援サイトでオリキャラたちの漫画を描いています。"
      },
      {
        "type": "text",
        "content": "\r\nたまに無料公開もしていますので、気軽に遊びに来てください～"
      },
      {
        "type": "text",
        "content": "\r\nファンボックス)"
      },
      {
        "type": "text",
        "content": "https://nekom.fanbox.cc/"
      },
      {
        "type": "text",
        "content": "\r\nファンティア)"
      },
      {
        "type": "text",
        "content": "https://fantia.jp/fanclubs/23611"
      },
      {
        "type": "text",
        "content": "\r\n・企画・プロット・イラスト:猫麦(@09ra_19ra)"
      },
      {
        "type": "text",
        "content": "\r\n・音声制作:マヨタマ様(@_mayotama_)"
      },
      {
        "type": "text",
        "content": "\r\n・CV:柚木つばめ様(@re_re_tsubame)"
      },
      {
        "type": "text",
        "content": "\r\n・CV:陽向葵ゅか様(@yukanyan2525)"
      },
      {
        "type": "text",
        "content": "\r\n・ロゴ・デザイン:nzworks様(@_nzworks_)"
      },
      {
        "type": "text",
        "content": "\r\n・シナリオ:白鴉鼎様(@hakuakanae)"
      },
      {
        "type": "text",
        "content": "\r\n・音声編集:atelier AUTH_QUID様"
      },
      {
        "type": "text",
        "content": "\r\n・映像制作: GriOni:柴田 裕也様"
      }
    ],
    "dl_count": 22078,
    "price": 3300,
    "rate_average": 4.86,
    "wishlist_count": 17992,
    "rate_count_detail": [
      {
        "review_point": 1,
        "count": 0,
        "ratio": 0
      },
      {
        "review_point": 2,
        "count": 7,
        "ratio": 0
      },
      {
        "review_point": 3,
        "count": 40,
        "ratio": 2
      },
      {
        "review_point": 4,
        "count": 144,
        "ratio": 7
      },
      {
        "review_point": 5,
        "count": 1620,
        "ratio": 89
      }
    ]
  },
  {
    "rj_code": "RJ01410567",
    "site_id": "maniax",
    "title": "べろちゅー大好きアイドルと優越感MAXハーレム3P-売れっ子アイドル2人とラブラブべろちゅーしまくる濃厚密着3PナマハメSEX→ナマ中出し-【キス特化】",
    "circle": "みずのちょう",
    "release_date": "2025年07月02日",
    "description": "トップアイドル2人と濃厚べろちゅー3P!!\n\n    \n    \n          \n\n        \n\n          \n\n                                \n\n                        \n\n          \n\n            \n\n          \n\n        \n\n      \n\n\n\n    \n\n\n            \n  \n\n\n\n              \nCONCEPTS\n\n    \n    \n          \n\n        \n\n          \n\n                                \n\n                        \n\n          \n\n            \n売れっ子アイドルと濃厚べろちゅー3Pセックスができちゃう\"べろちゅー特化型音声\"です\n\n          \n\n        \n\n      \n\n\n\n    \n\n\n            \n  \n\n\n\n              \nCHARACTERS\n\n    \n    \n          \n\n        \n\n          \n\n                                \n\n                        \n\n          \n\n            \n\n          \n\n        \n\n      \n\n\n\n    \n\n\n            \n  \n\n\n\n              \n★★トラック構成★★\n\n    \n    \n          \n\n        \n=========================================\n\r\n●01_【べろちゅー手コキ】超売れっ子アイドル2人と交互にべろちゅーする密着手コキ♪　10分42秒　(射精開始7分58秒)\n\r\n=========================================\n\r\n「今日の収録もう終わりだし、リップ落ちても平気だぜ～?　唾液ぐちょぐちょに混ぜ込んじゃえ」\n\r\n「三夜ちゃんドラマでも映画でも、キスシーンは絶対NGなのにね」\n\r\n「彼女にしたい女性芸能人ランキング、先月はるむが1位だったよ」\n\r\n\n\r\nちんこを触られる/乳首をいじられる/2人と交互にべろちゅー/耳元0cmで淫語囁き&実況　→るむとべろちゅーしながら手コキ射精\n\r\n↓\n\r\n2人に精液を味見される/2人に耳元でごっくんを聞かされる\n\r\n\n\r\n=========================================\n\r\n●02_【るむ本番】ライブ前にビジュ最強デカ乳トップアイドルとドキドキべろちゅー生ハメ♪　18分09秒　(挿入5分59秒,射精開始15分57秒)\n\r\n=========================================\n\r\n「ピーちゃん、るむもあたしもさ、アイドルだけど、偶像じゃないよ?　ステージで輝く女の子にも、こんなグロテスクな女性器がついてる。男性器にグニグニってしがみついて、精液搾り取って、受精して、子供をうむための穴…」\n\r\n「中に出してくれたらぁ…そのままタンポン押し込んで、精液溜めたままステージ上がってあげるぞ…?　みんなに笑顔振りまきながら…まんこはメスになってさ…?　『みんな～…大好きだよ～』って、手を振ってるときも…おまんこは精子まみれ…♪」\n\r\n\n\r\n2人と順番にべろちゅー/耳元0cmで淫語囁き&実況/2人のおっぱいを触る/乳首とちんこをいじられる　→勃起\n\r\n↓\n\r\nるむとナマSEX/2人と交互にべろちゅー/るむが耳元0cmで吐息喘ぎ/三夜が耳元0cmで淫語囁き&実況/るむのおっぱいを触る/乳首を責められる/生殖系淫語囁き　→るむにべろちゅーしながら中出し\n\r\n↓\n\r\nるむと余韻に浸るべろちゅー\n\r\n\n\r\n=========================================\n\r\n●03_【三夜本番】ライブ後に色白黒髪クール系トップアイドルと汗だくべろちゅー生ハメ♪　17分18秒　(挿入5分16秒,射精開始15分03秒)\n\r\n=========================================\n\r\n「今日のステージ、照明近すぎ。お客さんの熱気もすごくてさぁ、汗びっしょりになっちゃった。さすがに女臭いよね、ごめんね…?」\n\r\n「握手会のチケットを手に入れて、会場で何時間も待たされて、それでようやく、たった10秒握手できるかどうか。そんな大人気アイドルなんだよ?ルムたち。なのにプロデューサーさんだけは、レロレロ～ってよだれを溶かし合うベロチュー、粘膜と粘膜でぴったり密着…」\n\r\n\n\r\n2人と順番にべろちゅー/耳元0cmで淫語囁き&実況/三夜のおっぱいを触る/乳首を責められる/チンコをいじられる/三夜の腰を撫で回す/勃起する\n\r\n↓\n\r\n三夜とナマSEX/挿入後しばらく動かずまんこにチンコを馴染ませる/乳首を責められる/2人と交互にべろちゅー/三夜が耳元0cmで吐息喘ぎ/るむが耳元0cmで淫語囁き&実況/チンコを愛液でびしょ濡れにされる/2人のおっぱいを触る/生殖系淫語囁き　→三夜にべろちゅーしながら中出し\n\r\n↓\n\r\n三夜と余韻に浸るべろちゅー\n\r\n\n\r\n=========================================\n\r\n●04_【べろちゅー手コキ】パフェ食レポ直後の2人の口の甘さを味わういちゃいちゃ濃厚べろちゅー手コキ♪　13分13秒　(射精開始11分43秒)\n\r\n=========================================\n\r\n「ルムのおくち、甘い味するかな…ちゅ…れろれろ…ノドの奥から香ってくるでしょ…フルーツの甘い香り…ちゅっ…れろれろれろ…実はねー…?　食レポの企画で、三夜ちゃんとパフェ食べてきたの…」「ピーチとベリーのトロピカルパフェ…ちゅっ…すっごい美味しかった…ちゅっ…」\n\r\n「あたしは、小倉と抹茶の白玉パフェ…れりゅれりゅ…どうかなぁ…れろぉ…あたしのベロ、あんこの甘さ感じる…?　ちゅっ…」\n\r\n\n\r\n3人とも全裸で密着/2人のおっぱいを触る/チンコと乳首をいじられる/2人がまんこでオナニー/2人が交互に耳元0cmで吐息喘ぎ/2人と交互にべろちゅー/2人がべろちゅーしながら直前に収録で食べたパフェについて説明/2人のおっぱいを触る/2人の腰を撫でる　→三夜とべろちゅーしながら2人の手の中に射精/るむの耳舐め\n\r\n↓\n\r\n2人のどっちとSEXしたいかきかれる\n\r\n\n\r\n=========================================\n\r\n●05_【るむ本番】神乳トップアイドルと全裸で密着してべろちゅーナマ中出しで遺伝子を染み込ませる3PラブラブSEX♪　18分54秒　(挿入4分5秒,射精開始15分22秒)\n\r\n=========================================\n\r\n「過激めの恋愛ドラマでも、絶ーっ対写せないような、とっても濃厚でドスケベなキス。まんこのとこも、アップで写しますよー。…はーい、見えますか?　コンドームはつけてません。ナマのおちんちんを、ナマのおまんこに、何度もヌプヌプ出し入れして、2人は今、赤ちゃんができちゃうかもしれないセックス、してまーす」\n\r\n「なんか、思ったよりだいぶ恥ずかった…ぢゅるる…三夜ちゃん、やっぱカメラとめて…?」\n\r\n「やだ」\n\r\n\n\r\n2人と順番にべろちゅー/耳元0cmで淫語囁き/るむのおっぱいを触る/勃起する\n\r\n↓\n\r\nるむとナマSEX/2人と交互にべろちゅー/るむが耳元0cmで吐息喘ぎ/三夜が耳元0cmで淫語囁き&実況/乳首を責められる/耳舐めされる/セックスとべろちゅーを三夜にスマホで録画されて実況される/るむのおっぱいを触る/生殖系淫語囁き　→るむにべろちゅーしながら中出し\n\r\n↓\n\r\nるむと余韻に浸るべろちゅー\n\r\n\n\r\n=========================================\n\r\n●06_【三夜本番】艶髪トップアイドルと全裸で密着してべろちゅーナマ中出しで遺伝子を染み込ませる3PラブラブSEX♪　19分00秒　(挿入4分11秒,射精開始15分11秒)\n\r\n=========================================\n\r\n「マルチタレント遠藤三夜の、完璧に整ったお顔にブッチュー。性欲でネバネバになったツバ混ぜ混ぜ。女子の憧れのファッションリーダーの、紫外線対策バッチリの白い肌も、毎日手間かけてケアしてる黒髪も、もうプロデューサーさんだけのもの。ピンクの割れ目におちんぽハメて、三夜ちゃんのできたてプリプリ卵子、プロデューサーさんの精子でレ○プ。よわよわなポルチオに鈴口でチュウして、キレカワなトップアイドルの子宮に、濃厚おちんちんジュース注入っ」\n\r\n\n\r\n2人と順番にべろちゅー/耳元0cmで淫語囁き&実況/三夜の髪を触る/三夜の腰を撫でる/勃起する\n\r\n↓\n\r\n三夜とナマSEX/挿入後しばらく動かずまんこにチンコを馴染ませる/2人と交互にべろちゅー/三夜が耳元0cmで吐息喘ぎ/るむが耳元0cmで淫語囁き&実況/三夜のおっぱいを触る/三夜の汗まみれにされる/乳首を責められる/三夜のおっぱいを胸元に押し付けられる/生殖系淫語　→三夜にべろちゅーしながら中出し\n\r\n↓\n\r\n三夜と余韻に浸るべろちゅー\n\r\n\n\r\n=========================================\n\r\n●07_【るむ即尺フェラ】芥田るむのノーハンド勃起チャレンジ♪【番外編】　7分54秒　(射精開始5分32秒)\n\r\n=========================================\n\r\n「ちゅ…これは適当に洗ってる味だよ…ちゅ…絶対そう…ちゅる…れろれろ…カリの溝のとこ、白いのついてるし…ちゅ…舌でコスると、ボロボロとれる…ちゅっ…ちゅぅ…汚いなぁ…♪」\n\r\n「可愛い曲も、カッコいい曲も、たくさん歌ってくれるるむの口が、今はピーちゃんのオナホール。ヌメヌメのあったかいヨダレはローション。筋肉ムキムキのベロはオナティッシュ」\n\r\n\n\r\nるむの即尺フェラ/三夜が耳元0cmで淫語囁き&実況/るむに舌でチンカス掃除される/るむにフェラされながら股間のニオイを嗅がれる/乳首を責められる　→るむに口内射精\n\r\n↓\n\r\nるむが耳元0cmでごっくんを聞かせてくれる\n\r\n\n\r\n=========================================\n\r\n●08_【三夜即尺フェラ】遠藤三夜のおしっこ直後のおちんちん舐め舐め♪【番外編】　7分55秒　(射精開始5分35秒)\n\r\n=========================================\n\r\n「んー、しょっぱい…じゅるる…じゅる…これおしっこの味…?」\n\r\n「尿道にまだ残ってそうだよなー、女子の尿道より長そうだし。おちんちんニオいそうなのに、三夜ちゃん躊躇なくちゅっちゅしちゃって。愛情深すぎ…てか、変態なだけ?」\n\r\n「普段とのギャップえぐいよねー。完全清純派のアイドルで、水着グラビアも断ってるのに。裏では男の足元にしゃがんで、こんなにねっとりエッロいフェラ」\n\r\n\n\r\n三夜の即尺フェラ/るむが耳元0cmで淫語囁き&実況/乳首を責められる/三夜にフェラされながら股間のニオイを嗅がれる/三夜がフェラ中に少しむせる/おしっこの穴を舌先でチロチロされる　→三夜に口内射精\n\r\n↓\n\r\n三夜が耳元0cmでごっくんを聞かせてくれる\n\r\n\n\r\n=========================================\n\r\n●99_フリートーク　合計約9分\n\r\n　それぞれ5分程度\n\r\n=========================================\n\r\n\n\r\n声優様のフリートーク*2です\n\n      \n\n\n    \n\n\n            \n  \n\n\n\n        \n    \n          \n\n        \n\n          \n\n                                \n\n                        \n\n          \n\n            \n白濁液にまみれた姿の差分イラストつき!\n\n          \n\n        \n\n      \n\n\n\n    \n\n\n            \n  \n\n\n\n        \n    \n          \n\n        \n★★収録内容★★\n\r\n・本編音声　※約2時間4分(重複なし)\n\r\n　　wav, wav(SE無し版), mp3, mp3(SE無し)\n\r\n・サムネイル等の画像\n\r\n・購入者特典の差分イラスト1枚\n\r\n・readme.txt\n\r\n・台本(script.txt)\n\r\n\n\r\n\n\r\n★★クレジット★★\n\r\n\n\r\nCV:陽向葵ゅか(@yukanyan2525),涼花みなせ(@suzuka_minase)\n\r\n音声編集:MeltyBeans(@meltybeans)\n\r\nイラスト:なな枕(@nanamakura01)\n\r\nデザイン:一色リオ(@RIO1SIKI)\n\r\nシナリオ:こおろぎアトリエ(@ScenarioKoa)/みずのちょう(@mizuno_cho)\n\r\n※敬称略。IDはX(旧Twitter)\n\r\n\n\r\npixivでサークル作品の台本の一部を公開中です\n\r\npixiv:\nhttps://www.pixiv.net/users/35314942/novels",
    "img_url": "//img.dlsite.jp/modpub/images2/work/doujin/RJ01411000/RJ01410567_img_main.jpg",
    "media": [
      "https://img.dlsite.jp/modpub/images2/work/doujin/RJ01411000/RJ01410567_img_main.jpg",
      "https://img.dlsite.jp/modpub/images2/work/doujin/RJ01411000/RJ01410567_img_smp1.jpg",
      "https://img.dlsite.jp/modpub/images2/work/doujin/RJ01411000/RJ01410567_img_smp2.jpg",
      "https://img.dlsite.jp/modpub/images2/work/doujin/RJ01411000/RJ01410567_img_smp3.jpg"
    ],
    "embeds": [],
    "chobit_url": "https://chobit.cc/embed/5rhal/b3o232ff?aid=gentleman_dl",
    "genres": [
      "2cv",
      "淫語",
      "芸能人/アイドル/モデル",
      "ハーレム",
      "ラブラブ/あまあま",
      "ささやき",
      "男性受け",
      "中出し",
      "複数プレイ/乱交"
    ],
    "cv": [
      "陽向葵ゅか",
      "涼花みなせ"
    ],
    "content_tokens": [
      {
        "type": "text",
        "content": "トップアイドル2人と濃厚べろちゅー3P!!"
      },
      {
        "type": "image",
        "url": "https://img.dlsite.jp/modpub/images2/parts/RJ01411000/RJ01410567/0e3d244340be7d64a83f86bfe12bfc7b.jpg"
      },
      {
        "type": "text",
        "content": "CONCEPTS"
      },
      {
        "type": "image",
        "url": "https://img.dlsite.jp/modpub/images2/parts/RJ01411000/RJ01410567/4e69c90b25c0b30d649a20dfd360a22c.jpg"
      },
      {
        "type": "text",
        "content": "売れっ子アイドルと濃厚べろちゅー3Pセックスができちゃう\"べろちゅー特化型音声\"です"
      },
      {
        "type": "text",
        "content": "CHARACTERS"
      },
      {
        "type": "image",
        "url": "https://img.dlsite.jp/modpub/images2/parts/RJ01411000/RJ01410567/cc1cc6208becb56f87d33171adcfa732.jpg"
      },
      {
        "type": "text",
        "content": "★★トラック構成★★"
      },
      {
        "type": "text",
        "content": "========================================="
      },
      {
        "type": "text",
        "content": "\r\n●01_【べろちゅー手コキ】超売れっ子アイドル2人と交互にべろちゅーする密着手コキ♪　10分42秒　(射精開始7分58秒)"
      },
      {
        "type": "text",
        "content": "\r\n========================================="
      },
      {
        "type": "text",
        "content": "\r\n「今日の収録もう終わりだし、リップ落ちても平気だぜ～?　唾液ぐちょぐちょに混ぜ込んじゃえ」"
      },
      {
        "type": "text",
        "content": "\r\n「三夜ちゃんドラマでも映画でも、キスシーンは絶対NGなのにね」"
      },
      {
        "type": "text",
        "content": "\r\n「彼女にしたい女性芸能人ランキング、先月はるむが1位だったよ」"
      },
      {
        "type": "text",
        "content": "\r\nちんこを触られる/乳首をいじられる/2人と交互にべろちゅー/耳元0cmで淫語囁き&実況　→るむとべろちゅーしながら手コキ射精"
      },
      {
        "type": "text",
        "content": "\r\n↓"
      },
      {
        "type": "text",
        "content": "\r\n2人に精液を味見される/2人に耳元でごっくんを聞かされる"
      },
      {
        "type": "text",
        "content": "\r\n========================================="
      },
      {
        "type": "text",
        "content": "\r\n●02_【るむ本番】ライブ前にビジュ最強デカ乳トップアイドルとドキドキべろちゅー生ハメ♪　18分09秒　(挿入5分59秒,射精開始15分57秒)"
      },
      {
        "type": "text",
        "content": "\r\n========================================="
      },
      {
        "type": "text",
        "content": "\r\n「ピーちゃん、るむもあたしもさ、アイドルだけど、偶像じゃないよ?　ステージで輝く女の子にも、こんなグロテスクな女性器がついてる。男性器にグニグニってしがみついて、精液搾り取って、受精して、子供をうむための穴…」"
      },
      {
        "type": "text",
        "content": "\r\n「中に出してくれたらぁ…そのままタンポン押し込んで、精液溜めたままステージ上がってあげるぞ…?　みんなに笑顔振りまきながら…まんこはメスになってさ…?　『みんな～…大好きだよ～』って、手を振ってるときも…おまんこは精子まみれ…♪」"
      },
      {
        "type": "text",
        "content": "\r\n2人と順番にべろちゅー/耳元0cmで淫語囁き&実況/2人のおっぱいを触る/乳首とちんこをいじられる　→勃起"
      },
      {
        "type": "text",
        "content": "\r\n↓"
      },
      {
        "type": "text",
        "content": "\r\nるむとナマSEX/2人と交互にべろちゅー/るむが耳元0cmで吐息喘ぎ/三夜が耳元0cmで淫語囁き&実況/るむのおっぱいを触る/乳首を責められる/生殖系淫語囁き　→るむにべろちゅーしながら中出し"
      },
      {
        "type": "text",
        "content": "\r\n↓"
      },
      {
        "type": "text",
        "content": "\r\nるむと余韻に浸るべろちゅー"
      },
      {
        "type": "text",
        "content": "\r\n========================================="
      },
      {
        "type": "text",
        "content": "\r\n●03_【三夜本番】ライブ後に色白黒髪クール系トップアイドルと汗だくべろちゅー生ハメ♪　17分18秒　(挿入5分16秒,射精開始15分03秒)"
      },
      {
        "type": "text",
        "content": "\r\n========================================="
      },
      {
        "type": "text",
        "content": "\r\n「今日のステージ、照明近すぎ。お客さんの熱気もすごくてさぁ、汗びっしょりになっちゃった。さすがに女臭いよね、ごめんね…?」"
      },
      {
        "type": "text",
        "content": "\r\n「握手会のチケットを手に入れて、会場で何時間も待たされて、それでようやく、たった10秒握手できるかどうか。そんな大人気アイドルなんだよ?ルムたち。なのにプロデューサーさんだけは、レロレロ～ってよだれを溶かし合うベロチュー、粘膜と粘膜でぴったり密着…」"
      },
      {
        "type": "text",
        "content": "\r\n2人と順番にべろちゅー/耳元0cmで淫語囁き&実況/三夜のおっぱいを触る/乳首を責められる/チンコをいじられる/三夜の腰を撫で回す/勃起する"
      },
      {
        "type": "text",
        "content": "\r\n↓"
      },
      {
        "type": "text",
        "content": "\r\n三夜とナマSEX/挿入後しばらく動かずまんこにチンコを馴染ませる/乳首を責められる/2人と交互にべろちゅー/三夜が耳元0cmで吐息喘ぎ/るむが耳元0cmで淫語囁き&実況/チンコを愛液でびしょ濡れにされる/2人のおっぱいを触る/生殖系淫語囁き　→三夜にべろちゅーしながら中出し"
      },
      {
        "type": "text",
        "content": "\r\n↓"
      },
      {
        "type": "text",
        "content": "\r\n三夜と余韻に浸るべろちゅー"
      },
      {
        "type": "text",
        "content": "\r\n========================================="
      },
      {
        "type": "text",
        "content": "\r\n●04_【べろちゅー手コキ】パフェ食レポ直後の2人の口の甘さを味わういちゃいちゃ濃厚べろちゅー手コキ♪　13分13秒　(射精開始11分43秒)"
      },
      {
        "type": "text",
        "content": "\r\n========================================="
      },
      {
        "type": "text",
        "content": "\r\n「ルムのおくち、甘い味するかな…ちゅ…れろれろ…ノドの奥から香ってくるでしょ…フルーツの甘い香り…ちゅっ…れろれろれろ…実はねー…?　食レポの企画で、三夜ちゃんとパフェ食べてきたの…」「ピーチとベリーのトロピカルパフェ…ちゅっ…すっごい美味しかった…ちゅっ…」"
      },
      {
        "type": "text",
        "content": "\r\n「あたしは、小倉と抹茶の白玉パフェ…れりゅれりゅ…どうかなぁ…れろぉ…あたしのベロ、あんこの甘さ感じる…?　ちゅっ…」"
      },
      {
        "type": "text",
        "content": "\r\n3人とも全裸で密着/2人のおっぱいを触る/チンコと乳首をいじられる/2人がまんこでオナニー/2人が交互に耳元0cmで吐息喘ぎ/2人と交互にべろちゅー/2人がべろちゅーしながら直前に収録で食べたパフェについて説明/2人のおっぱいを触る/2人の腰を撫でる　→三夜とべろちゅーしながら2人の手の中に射精/るむの耳舐め"
      },
      {
        "type": "text",
        "content": "\r\n↓"
      },
      {
        "type": "text",
        "content": "\r\n2人のどっちとSEXしたいかきかれる"
      },
      {
        "type": "text",
        "content": "\r\n========================================="
      },
      {
        "type": "text",
        "content": "\r\n●05_【るむ本番】神乳トップアイドルと全裸で密着してべろちゅーナマ中出しで遺伝子を染み込ませる3PラブラブSEX♪　18分54秒　(挿入4分5秒,射精開始15分22秒)"
      },
      {
        "type": "text",
        "content": "\r\n========================================="
      },
      {
        "type": "text",
        "content": "\r\n「過激めの恋愛ドラマでも、絶ーっ対写せないような、とっても濃厚でドスケベなキス。まんこのとこも、アップで写しますよー。…はーい、見えますか?　コンドームはつけてません。ナマのおちんちんを、ナマのおまんこに、何度もヌプヌプ出し入れして、2人は今、赤ちゃんができちゃうかもしれないセックス、してまーす」"
      },
      {
        "type": "text",
        "content": "\r\n「なんか、思ったよりだいぶ恥ずかった…ぢゅるる…三夜ちゃん、やっぱカメラとめて…?」"
      },
      {
        "type": "text",
        "content": "\r\n「やだ」"
      },
      {
        "type": "text",
        "content": "\r\n2人と順番にべろちゅー/耳元0cmで淫語囁き/るむのおっぱいを触る/勃起する"
      },
      {
        "type": "text",
        "content": "\r\n↓"
      },
      {
        "type": "text",
        "content": "\r\nるむとナマSEX/2人と交互にべろちゅー/るむが耳元0cmで吐息喘ぎ/三夜が耳元0cmで淫語囁き&実況/乳首を責められる/耳舐めされる/セックスとべろちゅーを三夜にスマホで録画されて実況される/るむのおっぱいを触る/生殖系淫語囁き　→るむにべろちゅーしながら中出し"
      },
      {
        "type": "text",
        "content": "\r\n↓"
      },
      {
        "type": "text",
        "content": "\r\nるむと余韻に浸るべろちゅー"
      },
      {
        "type": "text",
        "content": "\r\n========================================="
      },
      {
        "type": "text",
        "content": "\r\n●06_【三夜本番】艶髪トップアイドルと全裸で密着してべろちゅーナマ中出しで遺伝子を染み込ませる3PラブラブSEX♪　19分00秒　(挿入4分11秒,射精開始15分11秒)"
      },
      {
        "type": "text",
        "content": "\r\n========================================="
      },
      {
        "type": "text",
        "content": "\r\n「マルチタレント遠藤三夜の、完璧に整ったお顔にブッチュー。性欲でネバネバになったツバ混ぜ混ぜ。女子の憧れのファッションリーダーの、紫外線対策バッチリの白い肌も、毎日手間かけてケアしてる黒髪も、もうプロデューサーさんだけのもの。ピンクの割れ目におちんぽハメて、三夜ちゃんのできたてプリプリ卵子、プロデューサーさんの精子でレ○プ。よわよわなポルチオに鈴口でチュウして、キレカワなトップアイドルの子宮に、濃厚おちんちんジュース注入っ」"
      },
      {
        "type": "text",
        "content": "\r\n2人と順番にべろちゅー/耳元0cmで淫語囁き&実況/三夜の髪を触る/三夜の腰を撫でる/勃起する"
      },
      {
        "type": "text",
        "content": "\r\n↓"
      },
      {
        "type": "text",
        "content": "\r\n三夜とナマSEX/挿入後しばらく動かずまんこにチンコを馴染ませる/2人と交互にべろちゅー/三夜が耳元0cmで吐息喘ぎ/るむが耳元0cmで淫語囁き&実況/三夜のおっぱいを触る/三夜の汗まみれにされる/乳首を責められる/三夜のおっぱいを胸元に押し付けられる/生殖系淫語　→三夜にべろちゅーしながら中出し"
      },
      {
        "type": "text",
        "content": "\r\n↓"
      },
      {
        "type": "text",
        "content": "\r\n三夜と余韻に浸るべろちゅー"
      },
      {
        "type": "text",
        "content": "\r\n========================================="
      },
      {
        "type": "text",
        "content": "\r\n●07_【るむ即尺フェラ】芥田るむのノーハンド勃起チャレンジ♪【番外編】　7分54秒　(射精開始5分32秒)"
      },
      {
        "type": "text",
        "content": "\r\n========================================="
      },
      {
        "type": "text",
        "content": "\r\n「ちゅ…これは適当に洗ってる味だよ…ちゅ…絶対そう…ちゅる…れろれろ…カリの溝のとこ、白いのついてるし…ちゅ…舌でコスると、ボロボロとれる…ちゅっ…ちゅぅ…汚いなぁ…♪」"
      },
      {
        "type": "text",
        "content": "\r\n「可愛い曲も、カッコいい曲も、たくさん歌ってくれるるむの口が、今はピーちゃんのオナホール。ヌメヌメのあったかいヨダレはローション。筋肉ムキムキのベロはオナティッシュ」"
      },
      {
        "type": "text",
        "content": "\r\nるむの即尺フェラ/三夜が耳元0cmで淫語囁き&実況/るむに舌でチンカス掃除される/るむにフェラされながら股間のニオイを嗅がれる/乳首を責められる　→るむに口内射精"
      },
      {
        "type": "text",
        "content": "\r\n↓"
      },
      {
        "type": "text",
        "content": "\r\nるむが耳元0cmでごっくんを聞かせてくれる"
      },
      {
        "type": "text",
        "content": "\r\n========================================="
      },
      {
        "type": "text",
        "content": "\r\n●08_【三夜即尺フェラ】遠藤三夜のおしっこ直後のおちんちん舐め舐め♪【番外編】　7分55秒　(射精開始5分35秒)"
      },
      {
        "type": "text",
        "content": "\r\n========================================="
      },
      {
        "type": "text",
        "content": "\r\n「んー、しょっぱい…じゅるる…じゅる…これおしっこの味…?」"
      },
      {
        "type": "text",
        "content": "\r\n「尿道にまだ残ってそうだよなー、女子の尿道より長そうだし。おちんちんニオいそうなのに、三夜ちゃん躊躇なくちゅっちゅしちゃって。愛情深すぎ…てか、変態なだけ?」"
      },
      {
        "type": "text",
        "content": "\r\n「普段とのギャップえぐいよねー。完全清純派のアイドルで、水着グラビアも断ってるのに。裏では男の足元にしゃがんで、こんなにねっとりエッロいフェラ」"
      },
      {
        "type": "text",
        "content": "\r\n三夜の即尺フェラ/るむが耳元0cmで淫語囁き&実況/乳首を責められる/三夜にフェラされながら股間のニオイを嗅がれる/三夜がフェラ中に少しむせる/おしっこの穴を舌先でチロチロされる　→三夜に口内射精"
      },
      {
        "type": "text",
        "content": "\r\n↓"
      },
      {
        "type": "text",
        "content": "\r\n三夜が耳元0cmでごっくんを聞かせてくれる"
      },
      {
        "type": "text",
        "content": "\r\n========================================="
      },
      {
        "type": "text",
        "content": "\r\n●99_フリートーク　合計約9分"
      },
      {
        "type": "text",
        "content": "\r\n　それぞれ5分程度"
      },
      {
        "type": "text",
        "content": "\r\n========================================="
      },
      {
        "type": "text",
        "content": "\r\n声優様のフリートーク*2です"
      },
      {
        "type": "image",
        "url": "https://img.dlsite.jp/modpub/images2/parts/RJ01411000/RJ01410567/9290c49f477db60f24fd6528c7d871df.jpg"
      },
      {
        "type": "text",
        "content": "白濁液にまみれた姿の差分イラストつき!"
      },
      {
        "type": "text",
        "content": "★★収録内容★★"
      },
      {
        "type": "text",
        "content": "\r\n・本編音声　※約2時間4分(重複なし)"
      },
      {
        "type": "text",
        "content": "\r\n　　wav, wav(SE無し版), mp3, mp3(SE無し)"
      },
      {
        "type": "text",
        "content": "\r\n・サムネイル等の画像"
      },
      {
        "type": "text",
        "content": "\r\n・購入者特典の差分イラスト1枚"
      },
      {
        "type": "text",
        "content": "\r\n・readme.txt"
      },
      {
        "type": "text",
        "content": "\r\n・台本(script.txt)"
      },
      {
        "type": "text",
        "content": "\r\n★★クレジット★★"
      },
      {
        "type": "text",
        "content": "\r\nCV:陽向葵ゅか(@yukanyan2525),涼花みなせ(@suzuka_minase)"
      },
      {
        "type": "text",
        "content": "\r\n音声編集:MeltyBeans(@meltybeans)"
      },
      {
        "type": "text",
        "content": "\r\nイラスト:なな枕(@nanamakura01)"
      },
      {
        "type": "text",
        "content": "\r\nデザイン:一色リオ(@RIO1SIKI)"
      },
      {
        "type": "text",
        "content": "\r\nシナリオ:こおろぎアトリエ(@ScenarioKoa)/みずのちょう(@mizuno_cho)"
      },
      {
        "type": "text",
        "content": "\r\n※敬称略。IDはX(旧Twitter)"
      },
      {
        "type": "text",
        "content": "\r\npixivでサークル作品の台本の一部を公開中です"
      },
      {
        "type": "text",
        "content": "\r\npixiv:"
      },
      {
        "type": "text",
        "content": "https://www.pixiv.net/users/35314942/novels"
      }
    ],
    "dl_count": 3574,
    "price": 1430,
    "rate_average": 4.89,
    "wishlist_count": 6012,
    "rate_count_detail": [
      {
        "review_point": 1,
        "count": 0,
        "ratio": 0
      },
      {
        "review_point": 2,
        "count": 0,
        "ratio": 0
      },
      {
        "review_point": 3,
        "count": 5,
        "ratio": 1
      },
      {
        "review_point": 4,
        "count": 40,
        "ratio": 8
      },
      {
        "review_point": 5,
        "count": 405,
        "ratio": 90
      }
    ]
  },
  {
    "rj_code": "RJ01414688",
    "site_id": "maniax",
    "title": "【ゆるオホ×お手軽中出し】高嶺の花だと思っていたダウナー爆モテJKがセックスチケット(生ハメ可)をくれたので、キスハメから中出しまで遠慮なく堪能しまくる話",
    "circle": "はだか抱きまくら係",
    "release_date": "2025年06月22日",
    "description": "※弊サークルは、『一発抜いて紳士になろう』を理念に運営されております。作品内では社会通念に反する描写が多数存在しますが、これらは反社会的行動を推奨するものではなく、欲望をフィクションで発散していただくことを目的としたものです。紳士淑女の皆様におかれましては、一発抜いて紳士になっていただければ幸いです。\n\n\n\n\n\n【本編音声　内容紹介】\n\n#1ずっと片思いしていた爆乳幼馴染がセックスチケットをくれたので、貪るようにベロチューしながら処女ハメ中出しする話\n\n《対面立位/ファーストキス/尻揉み/処女ハメ/中出し》\n\n\n\n#2俺以外の告白は全部断ってる貞操観念の堅い女が、恋人ごっこ子作りで生ちんぽをデロデロに甘やかしてくれる話\n\n《正常位/恋人ごっこ/好き好きささやき/イチャイチャベロチュー/中出し》\n\n\n\n#3疲れてる時にはハグとキスで癒してくれる女友達が、甘々手コキで精液煮詰められてから即ハメ中出しで金玉スッキリさせてくれる話\n\n《手コキ/対面座位/キス/ハグ/コキ捨て中出し》\n\n\n\n#4ミニスカートからチラ見する幼馴染のデカ尻に金玉がイライラしたので、電車内での立ちバックで中出し用即席オナホになってもらう話\n\n《立ちバック/電車内セックス/子宮ノック/完全同意痴○ごっこ/優越感煽り/中出し》\n\n\n\n#5中出し直後の孕み頃おまんこを生ちんぽで掻き混ぜて受精を促した後、追い打ち種付け射精で確実に好きな女を孕ませる話\n\n《対面立位/電車内セックス/2連続生ハメ/中出し》\n\n\n\n#6朝からエッグい美少女JKの制服姿を見せられてムラムラしてしまってので、即抜きチケットを使ってオナホまんこに金玉の中身をぶちまけた話\n\n《対面立位/即抜き生ハメ/通学路セックス/遺伝子相性確認ハグ/中出し》\n\n\n\n#7自分のエロさに無自覚なダウナークラスメイトが授業中にエッロい雌フェロモンを振りまいて男子生徒を無差別に勃起させるので、休み時間になるたびに即効で保健室に連れ込んで生まんこパコりまくらなければ金玉が爆発してしまう話(あなたはヒロインからセックスチケットを貰っているので両想い生ハメで性欲を解消できるが、他の男子生徒はトイレでオナニーするくらいしか性欲の解消方法がない)\n\n《正常位/保健室セックス/種付けプレス/大しゅきホールド/孕ませ懇願ささやき/中出し》\n\n\n\n#8貰ったセックスチケットを全て使いきってしまったので、壁ドン告白で幼馴染JKを口説き落として彼女オナホになってもらう話\n\n《対面立位/告白/恋愛成就両想いセックス/好き好きささやき/中出し》\n\n\n\n#9オナニーしていたら丁度いいタイミングで彼女が来てくれたので、ティッシュの代わりに生まんこ使わせてもらう話\n\n《オナニーの仕上げ騎乗位/即ハメ/中出し》\n\n\n\n#10嫉妬深くてめんどくさかわいい彼女に玉揉み亀頭くすぐりで精液煮詰めまくられた後、仲直り対面座位で幸福感マックスの中出しをする話\n\n《対面座位/金玉マッサージ/亀頭くすぐり/甘々焦らし前戯/仕上げ即ハメ交尾/中出し》\n\n\n\n#11マゾまんこに一切の抵抗を許さない子宮コネコネ寝バック交尾で彼女の膣穴を念入りにほぐし、仕上げの大量中出しで極上受精アクメさせてあげる話\n\n《寝バック/マゾ雌いじめ甘々セックス/思いっきり体重かけて子宮口をぐりぐりしながら中出し/受精アクメ》\n\n\n\n#12ハグしてるだけで癒される最高の女と、甘ラブ成分たっぷりの全裸密着騎乗位で汗ばんだ肌をくっつけあいながら幸せベロキス子作りする話\n\n《全裸密着騎乗位/イチャラブ/ベロチュー/好き好き中出し》\n\n\n\n#13思いっきり中出し射精した後の心地良い余韻に浸りながら、大好きな彼女を生ハメ抱き枕にして眠りにつく話\n\n《入眠用トラック/生ハメ添い寝/ハグ/密着/吐息》\n\n\n\n\n\n\n\n【特典1　挿絵付き小説　内容紹介】\n\n挿絵イラスト10枚(立ち絵含む)+セリフ差分、射精差分など\n\n合計90ページ\n\n\n\n\n\n【特典2　書き下ろしエロ小説　内容紹介】\n\n2章構成　約12000文字\n\n\n\n(1)芸能活動を始めてすぐにトップクラスの人気が出た極上の雌が、その才能のすべてをチン媚びに使って甘々目覚ましフェラで精液根こそぎ搾り取ってくれる話\n\n《目覚ましフェラ/玉揉み/騎乗位/中出し》\n\n\n\n(2)トップアイドル2人にアナル舐めとフェラを同時にされて、極限まで煮詰まった精液を初対面の処女まんJKにコキ捨て中出しする話\n\n《アナル舐め/フェラ/バック/3P/処女ハメ/中出し》\n\n\n\n\n\n\n\n【キャスト】\n\nヒロイン役　餅梨あむ　さま\n\n\nhttps://x.com/mochiri_0909\n\n\n\n編集　あんあんじー　さま\n\n\nhttps://x.com/anchang_custum\n\n\n\nシナリオやイラストなど　はだか抱きまくら係\n\n\nhttps://twitter.com/numotu_degowasu\n\n      \n\n\n    \n\n\n            \n  \n\n\n\n        \n    \n          \n\n        \n\n                          \n\n                \nずっと片思いしていた爆乳幼馴染がセックスチケットをくれたので、貪るようにベロチューしながら処女ハメ中出しする話\n\n                \n21:00\n\n              \n\n                          \n\n                \n俺以外の告白は全部断ってる貞操観念の堅い女が、恋人ごっこ子作りで生ちんぽをデロデロに甘やかしてくれる話\n\n                \n12:30\n\n              \n\n                          \n\n                \n疲れてる時にはハグとキスで癒してくれる女友達が、甘々手コキで精液煮詰められてから即ハメ中出しで金玉スッキリさせてくれる話\n\n                \n15:02\n\n              \n\n                          \n\n                \nミニスカートからチラ見する幼馴染のデカ尻に金玉がイライラしたので、電車内での立ちバックで中出し用即席オナホになってもらう話\n\n                \n10:02\n\n              \n\n                          \n\n                \n中出し直後の孕み頃おまんこを生ちんぽで掻き混ぜて受精を促した後、追い打ち種付け射精で確実に好きな女を孕ませる話\n\n                \n20:27\n\n              \n\n                          \n\n                \n朝からエッグい美少女JKの制服姿を見せられてムラムラしてしまったので、即抜きチケットを使ってオナホまんこに金玉の中身をぶちまけた話\n\n                \n13:15\n\n              \n\n                          \n\n                \n自分のエロさに無自覚なダウナークラスメイトが授業中にエッロい雌フェロモンを振りまいて男子生徒を無差別に勃起させるので、休み時間になるたびに即効で保健室に連れ込んで生まんこパコり…\n\n                \n12:45\n\n              \n\n                          \n\n                \n貰ったセックスチケットを全て使いきってしまったので、壁ドン告白で幼馴染JKを口説き落として彼女オナホになってもらう話\n\n                \n14:12\n\n              \n\n                          \n\n                \nオナニーしていたら丁度いいタイミングで彼女が来てくれたので、ティッシュの代わりに生まんこ使わせてもらう話\n\n                \n4:19\n\n              \n\n                          \n\n                \n嫉妬深くてめんどくさかわいい彼女に玉揉み亀頭くすぐりで精液煮詰めまくられた後、仲直り対面座位で幸福感マックスの中出しをする話\n\n                \n23:30\n\n              \n\n                          \n\n                \nマゾまんこに一切の抵抗を許さない子宮コネコネ寝バック交尾で彼女の膣穴を念入りにほぐし、仕上げの大量中出しで極上受精アクメさせてあげる話\n\n                \n7:49\n\n              \n\n                          \n\n                \nハグしてるだけで癒される最高の女と、甘ラブ成分たっぷりの全裸密着騎乗位で汗ばんだ肌をくっつけあいながら幸せベロキス子作りする話\n\n                \n10:47\n\n              \n\n                          \n\n                \n思いっきり中出し射精した後の心地良い余韻に浸りながら、大好きな彼女を生ハメ抱き枕にして眠りにつく話\n\n                \n6:02",
    "img_url": "//img.dlsite.jp/modpub/images2/work/doujin/RJ01415000/RJ01414688_img_main.jpg",
    "media": [
      "https://img.dlsite.jp/modpub/images2/work/doujin/RJ01415000/RJ01414688_img_main.jpg",
      "https://img.dlsite.jp/modpub/images2/work/doujin/RJ01415000/RJ01414688_img_smp1.jpg",
      "https://img.dlsite.jp/modpub/images2/work/doujin/RJ01415000/RJ01414688_img_smp2.jpg",
      "https://img.dlsite.jp/modpub/images2/work/doujin/RJ01415000/RJ01414688_img_smp3.jpg",
      "https://img.dlsite.jp/modpub/images2/work/doujin/RJ01415000/RJ01414688_img_smp4.jpg",
      "https://img.dlsite.jp/modpub/images2/work/doujin/RJ01415000/RJ01414688_img_smp5.jpg",
      "https://img.dlsite.jp/modpub/images2/work/doujin/RJ01415000/RJ01414688_img_smp6.jpg",
      "https://img.dlsite.jp/modpub/images2/work/doujin/RJ01415000/RJ01414688_img_smp7.jpg",
      "https://img.dlsite.jp/modpub/images2/work/doujin/RJ01415000/RJ01414688_img_smp8.jpg",
      "https://img.dlsite.jp/modpub/images2/work/doujin/RJ01415000/RJ01414688_img_smp9.jpg",
      "https://img.dlsite.jp/modpub/images2/work/doujin/RJ01415000/RJ01414688_img_smp10.jpg"
    ],
    "embeds": [],
    "chobit_url": "https://chobit.cc/embed/7ltew/dyv9nyb8?aid=gentleman_dl",
    "genres": [
      "1cv",
      "学生",
      "ダウナー",
      "オホ声",
      "中出し",
      "巨乳/爆乳",
      "黒髪"
    ],
    "cv": [
      "餅梨あむ"
    ],
    "content_tokens": [
      {
        "type": "image",
        "url": "https://img.dlsite.jp/modpub/images2/parts/RJ01415000/RJ01414688/ceecf699aecdfdec12a24e7937fd6c1a.jpg"
      },
      {
        "type": "image",
        "url": "https://img.dlsite.jp/modpub/images2/parts/RJ01415000/RJ01414688/760b4326547c8ba3f1ff68c0efb31107.jpg"
      },
      {
        "type": "image",
        "url": "https://img.dlsite.jp/modpub/images2/parts/RJ01415000/RJ01414688/d932ac2c87cb67f80251ac36ffeda1f8.jpg"
      },
      {
        "type": "image",
        "url": "https://img.dlsite.jp/modpub/images2/parts/RJ01415000/RJ01414688/16d11b2dc890d28c21a4708985f37422.jpg"
      },
      {
        "type": "image",
        "url": "https://img.dlsite.jp/modpub/images2/parts/RJ01415000/RJ01414688/93a1006a4878d0d595d7a3dbb2ad03c5.jpg"
      },
      {
        "type": "image",
        "url": "https://img.dlsite.jp/modpub/images2/parts/RJ01415000/RJ01414688/5912bcf21956e65103eeb8e7d876a7d6.jpg"
      },
      {
        "type": "image",
        "url": "https://img.dlsite.jp/modpub/images2/parts/RJ01415000/RJ01414688/11f2b15edd1be773c97cbbeac2374a69.jpg"
      },
      {
        "type": "image",
        "url": "https://img.dlsite.jp/modpub/images2/parts/RJ01415000/RJ01414688/f595706c9f596c8acd9a16b87220c1c4.jpg"
      },
      {
        "type": "image",
        "url": "https://img.dlsite.jp/modpub/images2/parts/RJ01415000/RJ01414688/aaa53944fcf1bf2193c9901d2e27110d.jpg"
      },
      {
        "type": "image",
        "url": "https://img.dlsite.jp/modpub/images2/parts/RJ01415000/RJ01414688/d0718d9859886e3e33faa62c8fec10d7.jpg"
      },
      {
        "type": "image",
        "url": "https://img.dlsite.jp/modpub/images2/parts/RJ01415000/RJ01414688/f4c7f2ff7155ea4a7ca4e32bb08c885c.jpg"
      },
      {
        "type": "image",
        "url": "https://img.dlsite.jp/modpub/images2/parts/RJ01415000/RJ01414688/7905c9c956cea18bc8e5ad3f31cd0aa2.jpg"
      },
      {
        "type": "image",
        "url": "https://img.dlsite.jp/modpub/images2/parts/RJ01415000/RJ01414688/1f6ee4293853b095cbbb971cb92165b6.jpg"
      },
      {
        "type": "image",
        "url": "https://img.dlsite.jp/modpub/images2/parts/RJ01415000/RJ01414688/14e4b659cb92204cdb3d8f10b1f5e4fb.jpg"
      },
      {
        "type": "image",
        "url": "https://img.dlsite.jp/modpub/images2/parts/RJ01415000/RJ01414688/fc1168b6f0fed2565049f1cc3ff9d481.jpg"
      },
      {
        "type": "image",
        "url": "https://img.dlsite.jp/modpub/images2/parts/RJ01415000/RJ01414688/ff9b1bfd784e6e10a5767cb7b880a737.jpg"
      },
      {
        "type": "text",
        "content": "※弊サークルは、『一発抜いて紳士になろう』を理念に運営されております。作品内では社会通念に反する描写が多数存在しますが、これらは反社会的行動を推奨するものではなく、欲望をフィクションで発散していただくことを目的としたものです。紳士淑女の皆様におかれましては、一発抜いて紳士になっていただければ幸いです。"
      },
      {
        "type": "text",
        "content": "\n【本編音声　内容紹介】"
      },
      {
        "type": "text",
        "content": "\n#1ずっと片思いしていた爆乳幼馴染がセックスチケットをくれたので、貪るようにベロチューしながら処女ハメ中出しする話"
      },
      {
        "type": "text",
        "content": "\n《対面立位/ファーストキス/尻揉み/処女ハメ/中出し》"
      },
      {
        "type": "text",
        "content": "\n#2俺以外の告白は全部断ってる貞操観念の堅い女が、恋人ごっこ子作りで生ちんぽをデロデロに甘やかしてくれる話"
      },
      {
        "type": "text",
        "content": "\n《正常位/恋人ごっこ/好き好きささやき/イチャイチャベロチュー/中出し》"
      },
      {
        "type": "text",
        "content": "\n#3疲れてる時にはハグとキスで癒してくれる女友達が、甘々手コキで精液煮詰められてから即ハメ中出しで金玉スッキリさせてくれる話"
      },
      {
        "type": "text",
        "content": "\n《手コキ/対面座位/キス/ハグ/コキ捨て中出し》"
      },
      {
        "type": "text",
        "content": "\n#4ミニスカートからチラ見する幼馴染のデカ尻に金玉がイライラしたので、電車内での立ちバックで中出し用即席オナホになってもらう話"
      },
      {
        "type": "text",
        "content": "\n《立ちバック/電車内セックス/子宮ノック/完全同意痴○ごっこ/優越感煽り/中出し》"
      },
      {
        "type": "text",
        "content": "\n#5中出し直後の孕み頃おまんこを生ちんぽで掻き混ぜて受精を促した後、追い打ち種付け射精で確実に好きな女を孕ませる話"
      },
      {
        "type": "text",
        "content": "\n《対面立位/電車内セックス/2連続生ハメ/中出し》"
      },
      {
        "type": "text",
        "content": "\n#6朝からエッグい美少女JKの制服姿を見せられてムラムラしてしまってので、即抜きチケットを使ってオナホまんこに金玉の中身をぶちまけた話"
      },
      {
        "type": "text",
        "content": "\n《対面立位/即抜き生ハメ/通学路セックス/遺伝子相性確認ハグ/中出し》"
      },
      {
        "type": "text",
        "content": "\n#7自分のエロさに無自覚なダウナークラスメイトが授業中にエッロい雌フェロモンを振りまいて男子生徒を無差別に勃起させるので、休み時間になるたびに即効で保健室に連れ込んで生まんこパコりまくらなければ金玉が爆発してしまう話(あなたはヒロインからセックスチケットを貰っているので両想い生ハメで性欲を解消できるが、他の男子生徒はトイレでオナニーするくらいしか性欲の解消方法がない)"
      },
      {
        "type": "text",
        "content": "\n《正常位/保健室セックス/種付けプレス/大しゅきホールド/孕ませ懇願ささやき/中出し》"
      },
      {
        "type": "text",
        "content": "\n#8貰ったセックスチケットを全て使いきってしまったので、壁ドン告白で幼馴染JKを口説き落として彼女オナホになってもらう話"
      },
      {
        "type": "text",
        "content": "\n《対面立位/告白/恋愛成就両想いセックス/好き好きささやき/中出し》"
      },
      {
        "type": "text",
        "content": "\n#9オナニーしていたら丁度いいタイミングで彼女が来てくれたので、ティッシュの代わりに生まんこ使わせてもらう話"
      },
      {
        "type": "text",
        "content": "\n《オナニーの仕上げ騎乗位/即ハメ/中出し》"
      },
      {
        "type": "text",
        "content": "\n#10嫉妬深くてめんどくさかわいい彼女に玉揉み亀頭くすぐりで精液煮詰めまくられた後、仲直り対面座位で幸福感マックスの中出しをする話"
      },
      {
        "type": "text",
        "content": "\n《対面座位/金玉マッサージ/亀頭くすぐり/甘々焦らし前戯/仕上げ即ハメ交尾/中出し》"
      },
      {
        "type": "text",
        "content": "\n#11マゾまんこに一切の抵抗を許さない子宮コネコネ寝バック交尾で彼女の膣穴を念入りにほぐし、仕上げの大量中出しで極上受精アクメさせてあげる話"
      },
      {
        "type": "text",
        "content": "\n《寝バック/マゾ雌いじめ甘々セックス/思いっきり体重かけて子宮口をぐりぐりしながら中出し/受精アクメ》"
      },
      {
        "type": "text",
        "content": "\n#12ハグしてるだけで癒される最高の女と、甘ラブ成分たっぷりの全裸密着騎乗位で汗ばんだ肌をくっつけあいながら幸せベロキス子作りする話"
      },
      {
        "type": "text",
        "content": "\n《全裸密着騎乗位/イチャラブ/ベロチュー/好き好き中出し》"
      },
      {
        "type": "text",
        "content": "\n#13思いっきり中出し射精した後の心地良い余韻に浸りながら、大好きな彼女を生ハメ抱き枕にして眠りにつく話"
      },
      {
        "type": "text",
        "content": "\n《入眠用トラック/生ハメ添い寝/ハグ/密着/吐息》"
      },
      {
        "type": "text",
        "content": "\n【特典1　挿絵付き小説　内容紹介】"
      },
      {
        "type": "text",
        "content": "\n挿絵イラスト10枚(立ち絵含む)+セリフ差分、射精差分など"
      },
      {
        "type": "text",
        "content": "\n合計90ページ"
      },
      {
        "type": "text",
        "content": "\n【特典2　書き下ろしエロ小説　内容紹介】"
      },
      {
        "type": "text",
        "content": "\n2章構成　約12000文字"
      },
      {
        "type": "text",
        "content": "\n(1)芸能活動を始めてすぐにトップクラスの人気が出た極上の雌が、その才能のすべてをチン媚びに使って甘々目覚ましフェラで精液根こそぎ搾り取ってくれる話"
      },
      {
        "type": "text",
        "content": "\n《目覚ましフェラ/玉揉み/騎乗位/中出し》"
      },
      {
        "type": "text",
        "content": "\n(2)トップアイドル2人にアナル舐めとフェラを同時にされて、極限まで煮詰まった精液を初対面の処女まんJKにコキ捨て中出しする話"
      },
      {
        "type": "text",
        "content": "\n《アナル舐め/フェラ/バック/3P/処女ハメ/中出し》"
      },
      {
        "type": "text",
        "content": "\n【キャスト】"
      },
      {
        "type": "text",
        "content": "\nヒロイン役　餅梨あむ　さま"
      },
      {
        "type": "text",
        "content": "https://x.com/mochiri_0909"
      },
      {
        "type": "text",
        "content": "\n編集　あんあんじー　さま"
      },
      {
        "type": "text",
        "content": "https://x.com/anchang_custum"
      },
      {
        "type": "text",
        "content": "\nシナリオやイラストなど　はだか抱きまくら係"
      },
      {
        "type": "text",
        "content": "https://twitter.com/numotu_degowasu"
      },
      {
        "type": "text",
        "content": "ずっと片思いしていた爆乳幼馴染がセックスチケットをくれたので、貪るようにベロチューしながら処女ハメ中出しする話"
      },
      {
        "type": "text",
        "content": "21:00"
      },
      {
        "type": "text",
        "content": "俺以外の告白は全部断ってる貞操観念の堅い女が、恋人ごっこ子作りで生ちんぽをデロデロに甘やかしてくれる話"
      },
      {
        "type": "text",
        "content": "12:30"
      },
      {
        "type": "text",
        "content": "疲れてる時にはハグとキスで癒してくれる女友達が、甘々手コキで精液煮詰められてから即ハメ中出しで金玉スッキリさせてくれる話"
      },
      {
        "type": "text",
        "content": "15:02"
      },
      {
        "type": "text",
        "content": "ミニスカートからチラ見する幼馴染のデカ尻に金玉がイライラしたので、電車内での立ちバックで中出し用即席オナホになってもらう話"
      },
      {
        "type": "text",
        "content": "10:02"
      },
      {
        "type": "text",
        "content": "中出し直後の孕み頃おまんこを生ちんぽで掻き混ぜて受精を促した後、追い打ち種付け射精で確実に好きな女を孕ませる話"
      },
      {
        "type": "text",
        "content": "20:27"
      },
      {
        "type": "text",
        "content": "朝からエッグい美少女JKの制服姿を見せられてムラムラしてしまったので、即抜きチケットを使ってオナホまんこに金玉の中身をぶちまけた話"
      },
      {
        "type": "text",
        "content": "13:15"
      },
      {
        "type": "text",
        "content": "自分のエロさに無自覚なダウナークラスメイトが授業中にエッロい雌フェロモンを振りまいて男子生徒を無差別に勃起させるので、休み時間になるたびに即効で保健室に連れ込んで生まんこパコり…"
      },
      {
        "type": "text",
        "content": "12:45"
      },
      {
        "type": "text",
        "content": "貰ったセックスチケットを全て使いきってしまったので、壁ドン告白で幼馴染JKを口説き落として彼女オナホになってもらう話"
      },
      {
        "type": "text",
        "content": "14:12"
      },
      {
        "type": "text",
        "content": "オナニーしていたら丁度いいタイミングで彼女が来てくれたので、ティッシュの代わりに生まんこ使わせてもらう話"
      },
      {
        "type": "text",
        "content": "4:19"
      },
      {
        "type": "text",
        "content": "嫉妬深くてめんどくさかわいい彼女に玉揉み亀頭くすぐりで精液煮詰めまくられた後、仲直り対面座位で幸福感マックスの中出しをする話"
      },
      {
        "type": "text",
        "content": "23:30"
      },
      {
        "type": "text",
        "content": "マゾまんこに一切の抵抗を許さない子宮コネコネ寝バック交尾で彼女の膣穴を念入りにほぐし、仕上げの大量中出しで極上受精アクメさせてあげる話"
      },
      {
        "type": "text",
        "content": "7:49"
      },
      {
        "type": "text",
        "content": "ハグしてるだけで癒される最高の女と、甘ラブ成分たっぷりの全裸密着騎乗位で汗ばんだ肌をくっつけあいながら幸せベロキス子作りする話"
      },
      {
        "type": "text",
        "content": "10:47"
      },
      {
        "type": "text",
        "content": "思いっきり中出し射精した後の心地良い余韻に浸りながら、大好きな彼女を生ハメ抱き枕にして眠りにつく話"
      },
      {
        "type": "text",
        "content": "6:02"
      }
    ],
    "dl_count": 4998,
    "price": 1430,
    "rate_average": 4.88,
    "wishlist_count": 6857,
    "rate_count_detail": [
      {
        "review_point": 1,
        "count": 3,
        "ratio": 0
      },
      {
        "review_point": 2,
        "count": 0,
        "ratio": 0
      },
      {
        "review_point": 3,
        "count": 11,
        "ratio": 1
      },
      {
        "review_point": 4,
        "count": 36,
        "ratio": 6
      },
      {
        "review_point": 5,
        "count": 525,
        "ratio": 91
      }
    ]
  }
]